glug/__init__.py
glug/glug.py
glug-0.0.3.dist-info/DESCRIPTION.rst
glug-0.0.3.dist-info/METADATA
glug-0.0.3.dist-info/RECORD
glug-0.0.3.dist-info/WHEEL
glug-0.0.3.dist-info/metadata.json
glug-0.0.3.dist-info/top_level.txt
