Metadata-Version: 2.0
Name: glug
Version: 0.0.3
Summary: GLUG - A Gfycat Like Username Generator
Home-page: https://github.com/OpenApprenticeFoundation/GfycatLikeUsernameGenerator
Author: Jules Lasne - The OpenApprentice Foundation
Author-email: jules@openapprentice.org
License: UNKNOWN
Download-URL: https://github.com/OpenApprenticeFoundation/GfycatLikeUsernameGenerator/archive/0.0.3.tar.gz
Keywords: Gfycat,random,username,generator
Platform: UNKNOWN
Classifier: Development Status :: 3 - Alpha
Classifier: Intended Audience :: Developers
Classifier: License :: OSI Approved :: GNU General Public License v3 or later (GPLv3+)
Classifier: Natural Language :: English
Classifier: Topic :: Software Development :: Libraries :: Python Modules
